dbconnector/__init__.py
dbconnector/cli.py
dbconnector/connectors.py
dbconnector/exceptions.py
dbconnector/utils.py
easy_multidb_connector-0.2.1.dist-info/licenses/LICENSE
easy_multidb_connector-0.2.1.dist-info/METADATA
easy_multidb_connector-0.2.1.dist-info/WHEEL
easy_multidb_connector-0.2.1.dist-info/entry_points.txt
easy_multidb_connector-0.2.1.dist-info/top_level.txt
easy_multidb_connector-0.2.1.dist-info/RECORD
