Metadata-Version: 2.4
Name: easy-multidb-connector
Version: 0.2.1
Summary: Conexões simplificadas com bancos SQL/NoSQL
Author-email: Wuotans <matheus.silva231996@gmail.com>
Classifier: Programming Language :: Python :: 3
Classifier: License :: OSI Approved :: MIT License
Requires-Python: >=3.8
License-File: LICENSE
Provides-Extra: mysql
Requires-Dist: mysql-connector-python; extra == "mysql"
Provides-Extra: postgresql
Requires-Dist: psycopg2; extra == "postgresql"
Provides-Extra: oracle
Requires-Dist: cx_Oracle; extra == "oracle"
Provides-Extra: mssql
Requires-Dist: pyodbc; extra == "mssql"
Provides-Extra: mongodb
Requires-Dist: pymongo; extra == "mongodb"
Provides-Extra: redis
Requires-Dist: redis; extra == "redis"
Provides-Extra: cassandra
Requires-Dist: cassandra-driver; extra == "cassandra"
Provides-Extra: elasticsearch
Requires-Dist: elasticsearch; extra == "elasticsearch"
Provides-Extra: async
Requires-Dist: aiomysql; extra == "async"
Requires-Dist: asyncpg; extra == "async"
Requires-Dist: aioredis; extra == "async"
Requires-Dist: aioelasticsearch; extra == "async"
Provides-Extra: all
Requires-Dist: mysql-connector-python; extra == "all"
Requires-Dist: psycopg2; extra == "all"
Requires-Dist: cx_Oracle; extra == "all"
Requires-Dist: pyodbc; extra == "all"
Requires-Dist: pymongo; extra == "all"
Requires-Dist: redis; extra == "all"
Requires-Dist: cassandra-driver; extra == "all"
Requires-Dist: elasticsearch; extra == "all"
Requires-Dist: aiomysql; extra == "all"
Requires-Dist: asyncpg; extra == "all"
Requires-Dist: aioredis; extra == "all"
Requires-Dist: aioelasticsearch; extra == "all"
Requires-Dist: typing-extensions; extra == "all"
Requires-Dist: click; extra == "all"
Dynamic: license-file
